simple_cloud_site/__init__.py
simple_cloud_site/feeds.py
simple_cloud_site/files.py
simple_cloud_site/html.py
simple_cloud_site/site.py
simple_cloud_site/templates.py
simple_cloud_site/utils.py
simple_cloud_site/commands/__init__.py
simple_cloud_site/commands/apply_template.py
simple_cloud_site/commands/devserver.py
simple_cloud_site/commands/generate_feeds.py
simple_cloud_site/commands/indices.py
simple_cloud_site/commands/main.py
simple_cloud_site/commands/publish.py
simple_cloud_site-0.1.0.dist-info/METADATA
simple_cloud_site-0.1.0.dist-info/WHEEL
simple_cloud_site-0.1.0.dist-info/entry_points.txt
simple_cloud_site-0.1.0.dist-info/top_level.txt
simple_cloud_site-0.1.0.dist-info/RECORD
