Metadata-Version: 2.1
Name: simple-cloud-site
Version: 0.1.0
Summary: Tools for working with pure HTML static sites
Home-page: http://github.com/acdha/simple-cloud-site/
Author: Chris Adams
Author-email: chris@improbable.org
License: CC0
Platform: any
Classifier: Programming Language :: Python :: 3
Classifier: Development Status :: 4 - Beta
Classifier: Natural Language :: English
Classifier: Environment :: Web Environment
Classifier: Intended Audience :: Developers
Classifier: Topic :: Internet :: WWW/HTTP :: Dynamic Content
Requires-Dist: cliff
Requires-Dist: lxml
Requires-Dist: pyquery
Requires-Dist: python-dateutil
Requires-Dist: apache-libcloud
